painter.py
pypainter-0.0.2.dist-info/METADATA
pypainter-0.0.2.dist-info/WHEEL
pypainter-0.0.2.dist-info/top_level.txt
pypainter-0.0.2.dist-info/RECORD
