Metadata-Version: 2.1
Name: pypainter
Version: 0.0.2
Summary: tkinter_painter
Home-page: UNKNOWN
Author: pythonnlgs
License: UNKNOWN
Platform: UNKNOWN
